LICENSE
MANIFEST.in
README.md
setup.py
LimitState/LimitState.py
LimitState/__init__.py
LimitState.egg-info/PKG-INFO
LimitState.egg-info/SOURCES.txt
LimitState.egg-info/dependency_links.txt
LimitState.egg-info/requires.txt
LimitState.egg-info/top_level.txt