Metadata-Version: 2.4
Name: LimitState
Version: 0.0.2
Summary: Software for Advanced First Order Second Moment Reliability Method
Home-page: https://github.com/ShinsukeSakai0321/LimitState
Author: Shinsuke Sakai
Author-email: sakaishin0321@gmail.com
License: MIT
Classifier: Programming Language :: Python :: 3
Classifier: License :: OSI Approved :: MIT License
Classifier: Operating System :: OS Independent
Requires-Python: >=3.6
License-File: LICENSE
Requires-Dist: numpy>=2.0.2
Requires-Dist: scipy>=1.13.1
Requires-Dist: pandas>=2.2.3
Requires-Dist: sympy>=1.13.3
Requires-Dist: pyDOE>=0.3.8
Dynamic: author
Dynamic: author-email
Dynamic: classifier
Dynamic: description
Dynamic: description-content-type
Dynamic: home-page
Dynamic: license
Dynamic: license-file
Dynamic: requires-dist
Dynamic: requires-python
Dynamic: summary
